armada/__init__.py
armada/config.py
armada/hermes.py
armada/service_discovery.py
armada-1.8.dist-info/LICENSE
armada-1.8.dist-info/METADATA
armada-1.8.dist-info/WHEEL
armada-1.8.dist-info/top_level.txt
armada-1.8.dist-info/RECORD
