Metadata-Version: 2.1
Name: armada
Version: 1.8
Summary: Configuration manager for ArmadaPlatform services.
Home-page: https://github.com/armadaplatform/armada-py
Author: Ganymede
Author-email: cerebro@ganymede.eu
License: UNKNOWN
Download-URL: https://github.com/armadaplatform/armada-py/tarball/1.3
Keywords: armada,hermes,config
Platform: UNKNOWN
License-File: LICENSE
